alauda_test-0.1.0.dist-info/RECORD
alauda_test-0.1.0.dist-info/metadata.json
alauda_test-0.1.0.dist-info/DESCRIPTION.rst
alauda_test-0.1.0.dist-info/entry_points.txt
alauda_test-0.1.0.dist-info/WHEEL
alauda_test-0.1.0.dist-info/top_level.txt
alauda_test-0.1.0.dist-info/METADATA
alaudacli/cmd_parser.py
alaudacli/compose.py
alaudacli/__init__.py
alaudacli/util.py
alaudacli/exceptions.py
alaudacli/project.py
alaudacli/service.py
alaudacli/settings.py
alaudacli/backup.py
alaudacli/instance.py
alaudacli/cmd_processor.py
alaudacli/alauda_cli.py
alaudacli/commands.py
alaudacli/organization.py
alaudacli/auth.py
clitests/parser_tests.py
clitests/__init__.py
clitests/e2e_tests.py
clitests/auto-scaling.cfg
