Metadata-Version: 2.0
Name: alauda-test
Version: 0.1.0
Summary: Alauda CLI
Home-page: https://www.alauda.io
Author: alauda.io
Author-email: info@mathildetech.com
License: UNKNOWN
Keywords: alauda
Platform: UNKNOWN
Classifier: Development Status :: 3 - Alpha
Classifier: Intended Audience :: Developers
Classifier: Topic :: Software Development :: Build Tools
Classifier: Programming Language :: Python :: 2
Classifier: Programming Language :: Python :: 2.6
Classifier: Programming Language :: Python :: 2.7
Classifier: Programming Language :: Python :: 3
Classifier: Programming Language :: Python :: 3.2
Classifier: Programming Language :: Python :: 3.3
Classifier: Programming Language :: Python :: 3.4
